darkutils/__init__.py
darkutils/c2_modules/__init__.py
darkutils/c2_modules/build.py
darkutils/c2_modules/cookiesteal.py
darkutils/c2_modules/encrypt.py
darkutils/c2_modules/identifiers.py
darkutils-4.0.dist-info/LICENSE
darkutils-4.0.dist-info/METADATA
darkutils-4.0.dist-info/WHEEL
darkutils-4.0.dist-info/top_level.txt
darkutils-4.0.dist-info/RECORD
