Metadata-Version: 2.1
Name: darkutils
Version: 4.0
Summary: Collection of modules by darkArp
Home-page: https://github.com/darkarp
Download-URL: https://github.com/darkarp/darkutils/archive/v4.0.tar.gz
Author: Mario Nascimento
Author-email: marionascimento@itsec.bz
License: MIT
Keywords: darkutils,encryption,c2
Classifier: Development Status :: 3 - Alpha
Classifier: Intended Audience :: Developers
Classifier: Topic :: Software Development :: Build Tools
Classifier: License :: OSI Approved :: MIT License
Classifier: Programming Language :: Python :: 3.5
Classifier: Programming Language :: Python :: 3.6
Classifier: Programming Language :: Python :: 3.7
Classifier: Programming Language :: Python :: 3.8
License-File: LICENSE
Requires-Dist: pexe37
